network_intrusion_detection/__init__.py
network_intrusion_detection/cnn_lstm_unsw_finetuned.h5
network_intrusion_detection/model.py
network_intrusion_detection/predict.py
network_intrusion_detection/preprocessing.py
network_intrusion_detection/tests/__init__.py
network_intrusion_detection/tests/test_predict.py
network_intrusion_detection/tests/test_preprocessing.py
network_intrusion_detection-0.1.4.dist-info/LICENSE
network_intrusion_detection-0.1.4.dist-info/METADATA
network_intrusion_detection-0.1.4.dist-info/WHEEL
network_intrusion_detection-0.1.4.dist-info/top_level.txt
network_intrusion_detection-0.1.4.dist-info/RECORD
