Metadata-Version: 2.1
Name: network_intrusion_detection
Version: 0.1.4
Summary: A Python package for CNN-LSTM model pre-trained on CICIDS2017 and finetuned on UNSW-NB15 for network intrusion detection.
Author: ID: 2319323
Author-email: 2319323@chester.ac.uk
Classifier: Programming Language :: Python :: 3
Classifier: License :: OSI Approved :: MIT License
Classifier: Operating System :: OS Independent
License-File: LICENSE
Requires-Dist: tensorflow
Requires-Dist: numpy
Requires-Dist: pandas
Requires-Dist: scikit-learn
Requires-Dist: imbalanced-learn
